{"cameraMode":{"drawMode":0,"name":"Shaded","section":"Shading Mode"},"sceneLighting":false,"audioPlay":false,"sceneViewState":{"m_AlwaysRefresh":false,"showFog":true,"showSkybox":false,"showFlares":true,"showImageEffects":true,"showParticleSystems":true,"showVisualEffectGraphs":true,"m_FxEnabled":true},"in2DMode":false,"pivot":{"x":19.87398338317871,"y":2.045405387878418,"z":5.791266441345215},"rotation":{"x":-0.03747858479619026,"y":-0.9525174498558044,"z":0.13113324344158173,"w":-0.2722446918487549},"size":4.200448036193848,"orthographic":false}