{"cameraMode":{"drawMode":0,"name":"Shaded","section":"Shading Mode"},"sceneLighting":true,"audioPlay":false,"sceneViewState":{"m_AlwaysRefresh":false,"showFog":true,"showSkybox":true,"showFlares":true,"showImageEffects":true,"showParticleSystems":true,"showVisualEffectGraphs":true,"m_FxEnabled":false},"in2DMode":false,"pivot":{"x":1714.0211181640625,"y":297.053955078125,"z":64.72763061523438},"rotation":{"x":-0.007434554398059845,"y":-0.991128146648407,"z":0.11681567132472992,"w":-0.06432414799928665},"size":607.9169311523438,"orthographic":false}